codeleak/__init__.py
codeleak/exceptions.py
codeleak/packer.py
codeleak/revealer.py
codeleak/utils.py
codeleak-1.0.0.dist-info/METADATA
codeleak-1.0.0.dist-info/WHEEL
codeleak-1.0.0.dist-info/entry_points.txt
codeleak-1.0.0.dist-info/top_level.txt
codeleak-1.0.0.dist-info/RECORD
