Metadata-Version: 2.4
Name: codeleak
Version: 1.0.0
Summary: Pack directories into HEX parts and reveal them back
Author-email: daehyunyun <nari08132@naver.com>
License: MIT
Project-URL: Homepage, https://github.com/yourname/codeleak
Project-URL: Issues, https://github.com/yourname/codeleak/issues
Keywords: hex,pack,tar,split,restore,utility
Classifier: Programming Language :: Python :: 3
Classifier: License :: OSI Approved :: MIT License
Classifier: Operating System :: OS Independent
Requires-Python: >=3.8
